gbe0_log/__init__.py
gbe0_log/__version__.py
gbe0_log/logger.py
gbe0_log-1.0.0.dist-info/LICENSE
gbe0_log-1.0.0.dist-info/METADATA
gbe0_log-1.0.0.dist-info/WHEEL
gbe0_log-1.0.0.dist-info/top_level.txt
gbe0_log-1.0.0.dist-info/RECORD
