Metadata-Version: 2.1
Name: gbe0-log
Version: 1.0.0
Summary: My standard logging module.
Home-page: https://github.com/python-modules/gbe0-log
Author: gbe0
Author-email: python@gbe0.com
License: MIT
Platform: UNKNOWN
Classifier: Intended Audience :: Developers
Classifier: Natural Language :: English
Classifier: License :: OSI Approved :: MIT License
Classifier: Programming Language :: Python
Classifier: Programming Language :: Python :: 3.6
Classifier: Programming Language :: Python :: 3.7
Classifier: Programming Language :: Python :: 3.8
Classifier: Programming Language :: Python :: 3.9
Requires-Python: >= 3.6
Requires-Dist: colorlog
